onesource_db/__init__.py
onesource_db/database.py
onesource_db/models/__init__.py
onesource_db/models/auth.py
onesource_db/models/base.py
onesource_db/models/public.py
onesource_db-0.1.0.dist-info/METADATA
onesource_db-0.1.0.dist-info/WHEEL
onesource_db-0.1.0.dist-info/top_level.txt
onesource_db-0.1.0.dist-info/RECORD
