Metadata-Version: 2.2
Name: onesource-db
Version: 0.1.0
Summary: The shared database for OneSource
Author: OneSource
Requires-Dist: sqlalchemy>=2.0.0
Requires-Dist: python-dotenv>=1.0.0
Requires-Dist: psycopg2-binary>=2.9.0
Dynamic: author
Dynamic: requires-dist
Dynamic: summary
